seqtag/__init__.py
seqtag/base_model.py
seqtag/config.py
seqtag/data_builder.py
seqtag/data_utils.py
seqtag/general_utils.py
seqtag/ner_model.py
seqtag/predictor.py
seqtag/trainer.py
seqtag-1.0.8.dist-info/LICENSE
seqtag-1.0.8.dist-info/METADATA
seqtag-1.0.8.dist-info/WHEEL
seqtag-1.0.8.dist-info/top_level.txt
seqtag-1.0.8.dist-info/RECORD
